README.rst
setup.cfg
setup.py
mqtt_codec/__init__.py
mqtt_codec/io.py
mqtt_codec/packet.py
mqtt_codec.egg-info/PKG-INFO
mqtt_codec.egg-info/SOURCES.txt
mqtt_codec.egg-info/dependency_links.txt
mqtt_codec.egg-info/requires.txt
mqtt_codec.egg-info/top_level.txt