Metadata-Version: 2.1
Name: mqtt-codec
Version: 1.0.1
Summary: Weapons grade MQTT packet codec.
Home-page: https://github.com/kcallin/mqtt-codec
Author: Keegan Callin
Author-email: kc@kcallin.net
License: UNKNOWN
Project-URL: Bug Tracker, https://github.com/kcallin/mqtt-codec/issues
Project-URL: Documentation, https://mqtt-codec.readthedocs.io/en/latest/
Project-URL: Source Code, https://github.com/kcallin/mqtt-codec
Platform: UNKNOWN
Classifier: Development Status :: 5 - Production/Stable
Classifier: Intended Audience :: Developers
Classifier: Topic :: Communications
Classifier: Topic :: Internet
Classifier: Topic :: Software Development
Classifier: Topic :: Software Development :: Libraries
Classifier: Topic :: Software Development :: Libraries :: Python Modules
Classifier: Programming Language :: Python
Classifier: Programming Language :: Python :: 2
Classifier: Programming Language :: Python :: 2.7
Classifier: Programming Language :: Python :: 3
Classifier: Programming Language :: Python :: 3.4
Classifier: Programming Language :: Python :: 3.5
Classifier: Programming Language :: Python :: 3.6
Classifier: Programming Language :: Python :: 3.7
Classifier: License :: OSI Approved :: GNU Lesser General Public License v3 (LGPLv3)
Classifier: Operating System :: POSIX :: Linux
Requires-Python: >=2.7
